{
  "m_GameObject": {
    "m_FileID": 0,
    "m_PathID": 0
  },
  "m_Enabled": 1,
  "m_Script": {
    "m_FileID": 0,
    "m_PathID": 2773386506308366186
  },
  "m_Name": "fg_goroGhostWoods2204_h01",
  "cellSize": 256,
  "padding": 3,
  "atlasTextures": [
    {
      "m_FileID": 0,
      "m_PathID": -2067218391083274363
    }
  ],
  "textureDataList": [
    {
      "name": "fg_goroGhostWoods2204_h01",
      "atlasName": "fg_goroGhostWoods2204_h01_Atlas0",
      "width": 640,
      "height": 1024,
      "cellIndexList": [
        0,
        1,
        2,
        3,
        4,
        5,
        6,
        7,
        8,
        9,
        10,
        11,
        12,
        13,
        12
      ],
      "transparentIndex": 12
    },
    {
      "name": "fg_goroGhostWoods2204_h01b",
      "atlasName": "fg_goroGhostWoods2204_h01_Atlas0",
      "width": 640,
      "height": 1024,
      "cellIndexList": [
        0,
        1,
        2,
        3,
        4,
        5,
        6,
        7,
        8,
        14,
        15,
        11,
        12,
        16,
        12
      ],
      "transparentIndex": 12
    },
    {
      "name": "fg_goroGhostWoods2204_h01c",
      "atlasName": "fg_goroGhostWoods2204_h01_Atlas0",
      "width": 640,
      "height": 1024,
      "cellIndexList": [
        0,
        1,
        2,
        3,
        4,
        5,
        6,
        7,
        8,
        17,
        18,
        11,
        12,
        19,
        12
      ],
      "transparentIndex": 12
    },
    {
      "name": "fg_goroGhostWoods2204_h01d",
      "atlasName": "fg_goroGhostWoods2204_h01_Atlas0",
      "width": 640,
      "height": 1024,
      "cellIndexList": [
        0,
        1,
        2,
        3,
        4,
        5,
        6,
        7,
        8,
        20,
        21,
        11,
        12,
        22,
        12
      ],
      "transparentIndex": 12
    },
    {
      "name": "fg_goroGhostWoods2204_h01e",
      "atlasName": "fg_goroGhostWoods2204_h01_Atlas0",
      "width": 640,
      "height": 1024,
      "cellIndexList": [
        0,
        1,
        2,
        3,
        4,
        5,
        6,
        7,
        8,
        23,
        24,
        11,
        12,
        25,
        12
      ],
      "transparentIndex": 12
    },
    {
      "name": "fg_goroGhostWoods2204_h01f",
      "atlasName": "fg_goroGhostWoods2204_h01_Atlas0",
      "width": 640,
      "height": 1024,
      "cellIndexList": [
        0,
        1,
        2,
        3,
        4,
        5,
        6,
        7,
        8,
        26,
        27,
        11,
        12,
        28,
        12
      ],
      "transparentIndex": 12
    }
  ]
}