{
  "m_GameObject": {
    "m_FileID": 0,
    "m_PathID": 0
  },
  "m_Enabled": 1,
  "m_Script": {
    "m_FileID": 0,
    "m_PathID": -657477701292886207
  },
  "m_Name": "skill_akashi_s01_01",
  "m_Version": 0,
  "m_Tracks": [
    {
      "m_FileID": 0,
      "m_PathID": 7354804757951295725
    },
    {
      "m_FileID": 0,
      "m_PathID": 6102450173640488786
    },
    {
      "m_FileID": 0,
      "m_PathID": 6954286578671644146
    },
    {
      "m_FileID": 0,
      "m_PathID": -171184947993222109
    },
    {
      "m_FileID": 0,
      "m_PathID": -1206337992204286626
    },
    {
      "m_FileID": 0,
      "m_PathID": 8289902489119496844
    }
  ],
  "m_FixedDuration": 0.0,
  "m_EditorSettings": {
    "m_Framerate": 30.0
  },
  "m_DurationMode": 0,
  "m_MarkerTrack": {
    "m_FileID": 0,
    "m_PathID": -684944720361225471
  }
}