{
  "m_GameObject": {
    "m_FileID": 0,
    "m_PathID": 0
  },
  "m_Enabled": 1,
  "m_Script": {
    "m_FileID": 1,
    "m_PathID": -657477701292886207
  },
  "m_Name": "skill_koukih01_03",
  "m_Version": 0,
  "m_Tracks": [
    {
      "m_FileID": 0,
      "m_PathID": 2166034178488039777
    },
    {
      "m_FileID": 0,
      "m_PathID": 3967756637621601389
    },
    {
      "m_FileID": 0,
      "m_PathID": -6149378586239751800
    },
    {
      "m_FileID": 0,
      "m_PathID": -8524965255682244412
    },
    {
      "m_FileID": 0,
      "m_PathID": -4091805227278016287
    },
    {
      "m_FileID": 0,
      "m_PathID": -5929026144645089753
    },
    {
      "m_FileID": 0,
      "m_PathID": 5457174467242975692
    },
    {
      "m_FileID": 0,
      "m_PathID": -2983074662037424407
    },
    {
      "m_FileID": 0,
      "m_PathID": 1619661821961217693
    },
    {
      "m_FileID": 0,
      "m_PathID": -7730564609104535704
    }
  ],
  "m_FixedDuration": 0.0,
  "m_EditorSettings": {
    "m_Framerate": 60.0
  },
  "m_DurationMode": 0,
  "m_MarkerTrack": {
    "m_FileID": 0,
    "m_PathID": -4562899214122275676
  }
}